tasrif/__init__.py
tasrif/yaml_parser.py
tasrif/data_readers/__init__.py
tasrif/data_readers/fitbit_interday_dataset.py
tasrif/data_readers/fitbit_intraday_dataset.py
tasrif/data_readers/my_heart_counts.py
tasrif/data_readers/siha_dataset.py
tasrif/data_readers/sleep_health.py
tasrif/data_readers/withings_dataset.py
tasrif/data_readers/zenodo_fitbit_dataset.py
tasrif/processing_pipeline/__init__.py
tasrif/processing_pipeline/compose_operator.py
tasrif/processing_pipeline/map_iterable_operator.py
tasrif/processing_pipeline/map_processing_operator.py
tasrif/processing_pipeline/noop_operator.py
tasrif/processing_pipeline/observer.py
tasrif/processing_pipeline/pandas_operator.py
tasrif/processing_pipeline/parallel_operator.py
tasrif/processing_pipeline/print_operator.py
tasrif/processing_pipeline/processing_operator.py
tasrif/processing_pipeline/reduce_processing_operator.py
tasrif/processing_pipeline/scoped_processing_operator.py
tasrif/processing_pipeline/sequence_operator.py
tasrif/processing_pipeline/split_operator.py
tasrif/processing_pipeline/validators.py
tasrif/processing_pipeline/variable.py
tasrif/processing_pipeline/custom/__init__.py
tasrif/processing_pipeline/custom/add_duration_operator.py
tasrif/processing_pipeline/custom/aggregate_activity_dates_operator.py
tasrif/processing_pipeline/custom/aggregate_operator.py
tasrif/processing_pipeline/custom/categorize_duration_operator.py
tasrif/processing_pipeline/custom/categorize_time_operator.py
tasrif/processing_pipeline/custom/create_feature_operator.py
tasrif/processing_pipeline/custom/distributed_upsample_operator.py
tasrif/processing_pipeline/custom/drop_index_duplicates_operator.py
tasrif/processing_pipeline/custom/encode_cyclical_features_operator.py
tasrif/processing_pipeline/custom/filter_operator.py
tasrif/processing_pipeline/custom/flatten_operator.py
tasrif/processing_pipeline/custom/iterate_json_operator.py
tasrif/processing_pipeline/custom/jq_operator.py
tasrif-0.1.0.dist-info/LICENSE
tasrif-0.1.0.dist-info/METADATA
tasrif-0.1.0.dist-info/NOTICE.txt
tasrif-0.1.0.dist-info/WHEEL
tasrif-0.1.0.dist-info/top_level.txt
tasrif-0.1.0.dist-info/RECORD
