Metadata-Version: 2.1
Name: tasrif
Version: 0.1.0
Summary: UNKNOWN
Home-page: https://github.com/qcri/tasrif
Author: QCRI
Author-email: uabbas@hbku.edu.qa
License: BSD-3-Clause
Platform: UNKNOWN
Classifier: Programming Language :: Python :: 3
Classifier: License :: OSI Approved :: BSD License
Classifier: Operating System :: OS Independent
Requires-Python: >= 3.7
License-File: LICENSE
License-File: NOTICE.txt
Requires-Dist: pandas (>=1.1.1)
Requires-Dist: numpy (<=1.20)
Requires-Dist: pyjq (>=2.5.1)
Requires-Dist: ummalqura (>=2.0.1)
Requires-Dist: scikit-learn (>=0.22.1)
Requires-Dist: tqdm (>=4.52.0)
Requires-Dist: ray (>=1.7.0)
Requires-Dist: dataprep (>=0.3.0)
